supervisor_logging_gelf/__init__.py
supervisor_logging_gelf-0.0.1.dist-info/DESCRIPTION.rst
supervisor_logging_gelf-0.0.1.dist-info/METADATA
supervisor_logging_gelf-0.0.1.dist-info/RECORD
supervisor_logging_gelf-0.0.1.dist-info/WHEEL
supervisor_logging_gelf-0.0.1.dist-info/entry_points.txt
supervisor_logging_gelf-0.0.1.dist-info/metadata.json
supervisor_logging_gelf-0.0.1.dist-info/top_level.txt
