Metadata-Version: 2.0
Name: supervisor-logging-gelf
Version: 0.0.1
Summary: Stream supervisord logs to a Graylog instance
Home-page: https://github.com/PerformLine/supervisor-logging-gelf
Author: PerformLine Engineering
Author-email: nathan@performline.com
License: Apache 2.0
Platform: UNKNOWN
Requires-Dist: graypy
Requires-Dist: supervisor
